errorgnomark/__init__.py
errorgnomark/configuration.py
errorgnomark/errorgnomarker.py
errorgnomark/execute.py
errorgnomark/fake_data.py
errorgnomark/simulator.py
errorgnomark/token_manager.py
errorgnomark/cirpulse_generator/__init__.py
errorgnomark/cirpulse_generator/circuit_generator.py
errorgnomark/cirpulse_generator/elements.py
errorgnomark/cirpulse_generator/others.py
errorgnomark/cirpulse_generator/pulse_generator.py
errorgnomark/cirpulse_generator/qubit_selector.py
errorgnomark/data_analysis/__init__.py
errorgnomark/data_analysis/layer_cirgate.py
errorgnomark/data_analysis/layer_device.py
errorgnomark/results_tools/__init__.py
errorgnomark/results_tools/egm_report_tools.py
errorgnomark/results_tools/visualization.py
errorgnomark-0.1.9.dist-info/licenses/LICENSE
errorgnomark-0.1.9.dist-info/METADATA
errorgnomark-0.1.9.dist-info/WHEEL
errorgnomark-0.1.9.dist-info/top_level.txt
errorgnomark-0.1.9.dist-info/RECORD
