Metadata-Version: 2.4
Name: ErrorGnoMark
Version: 0.1.9
Summary: A Toolkit for Error Diagnosis and Benchmarking for Quantum Chip
Home-page: https://github.com/BAQIS-Quantum/ErrorGnoMark
Author: Chai Xudan, Wang Jingbo, Xiaoxiao
Author-email: chaixd@baqis.ac.cn
License: Apache License 2.0
Keywords: errorgnomark,quantum benchmarking,quantum computing,quantum operating system
Classifier: Programming Language :: Python :: 3
Classifier: Programming Language :: Python :: 3.10
Classifier: License :: OSI Approved :: Apache Software License
Classifier: Operating System :: OS Independent
Classifier: Intended Audience :: Developers
Classifier: Topic :: Scientific/Engineering :: Physics
Requires-Python: >=3.10
License-File: LICENSE
Dynamic: author
Dynamic: author-email
Dynamic: classifier
Dynamic: description
Dynamic: description-content-type
Dynamic: home-page
Dynamic: keywords
Dynamic: license
Dynamic: license-file
Dynamic: requires-python
Dynamic: summary
